{
    "nlm_catalog": "M0058396-031",
    "input_file_number": "W1NLM483-I1NLM483",
    "language(s)_of_the_main_text_(үндсэн_хэл)": "Tibetan",
    "other_language(s)_in_the_main_text_(бусад_оролцсон_хэл)": "N",
    "full_title_(бүтэн_гарчиг)": "` RTA'I GA-YANG 'GUGS PA'I CHO GA ZHES BYA BA BZHUGS SO, ,",
    "colophon_(төгсгөлийн_үг)": "@005B (CES RTA GA-YANG 'GUGS CHO GA 'DI NI YUL MI RNAMS RTA'I GA-YANG SHIN TU SAM THAG LA, BYAMS PA'I SEMS KYIS KUN NAS BSRUNGS STE THA SHAL RMYONG BA'I SPYOD YUL NA, SU TE KARMA MING CANG GYIS, SLOB DPON CHEN PO PADMA 'BYUNG GNAS KYI GA-YANG 'GUGS SOGS LA BDANG BYAS NAS 'PHRAL DU BRIS PA'O,)",
    "author_simple": "SU TE KARMA,",
    "cover_type_(хавтасны_төрөл)": "N/A",
    "condition_of_book_(номын_төлөв_байдал)": "GOOD",
    "readability_of_book_(уншигдах_гаргацны_тухай)": "MEDIUM",
    "volume_(боть)": "N",
    "page_numbers_(хуудасны_дугаар)": "1A-5B",
    "size_of_printed_area_(дотоод_бичвэрийн_хэмжээ)": "28.5x6",
    "size_of_pages_(хуудасны_хэмжээ)": "33x8",
    "text_format_(бичвэрийн_төлөв)": "MS",
    "cataloger-gerelmaa": "shar",
    "source": "National Library of Mongolia",
    "processing_history": [
        {
            "timestamp": "2024-09-14T00:11:21.797439+00:00",
            "processor": "MongoliaCatalogProcessor",
            "action": "created"
        }
    ]
}