{
    "nlm_catalog": "M0058535-012",
    "input_file_number": "W1NLM622-I1N1M622",
    "language(s)_of_the_main_text_(үндсэн_хэл)": "Tibetan",
    "other_language(s)_in_the_main_text_(бусад_оролцсон_хэл)": "N",
    "full_title_(бүтэн_гарчиг)": "*, ,BAR DO'I SEMS CAN LA CHU SBYIN GTOR MA BSUR GTONG TSUL BZHUGS SO, ,",
    "author's_name_(_зохиогч)": "BLO BZANG T'A RA,",
    "dates_of_the_author_(зохиогдсон_өдөр)": "CHU PHO STAG LO'I DGUN ZLA 'BRING PO'I MKHA' 'GRO 'DU BA'I DUS BZANG,",
    "translator_(орчуулагч)": "",
    "dates_of_the_translator_(орчуулагдсан_өдөр)": "",
    "editor_(хянан_тохиолдуулагч)": "",
    "dates_of_the_editor_(хянан_тохиолдуулсан_өдөр)": "",
    "year_of_this_edition_(дахин_засварлан_хэвлэсэн_өдөр)": "",
    "format_of_the_book_(номын_формат)": "",
    "cover_type_(хавтасны_төрөл)": "N/a",
    "condition_of_book_(номын_төлөв_байдал)": "Medium",
    "readability_of_book_(уншигдах_гаргацны_тухай)": "Good",
    "volume_(боть)": "N",
    "page_numbers_(хуудасны_дугаар)": "1A-10A INC [*Missing page from 8A-8B *]",
    "size_of_printed_area_(дотоод_бичвэрийн_хэмжээ)": "16.5x6.5",
    "size_of_pages_(хуудасны_хэмжээ)": "21x8",
    "text_format_(бичвэрийн_төлөв)": "MS",
    "publisher_(хэвлэсэн_буюу_бүтээсэн_хийд_буюу_бархан)": "",
    "copyright_owner_(зохиогчийн_эрхийг_эзэмшигч)": "",
    "location_of_printing_(хэвлэсэн_орон_нутаг)": "",
    "colophon_(төгсгөлийн_үг)": "@010A *, ,(CES BAR DO GTOR MA PHAN BDE'I MCHOG SBYIN ZHES BYA BA 'DI NI, DPAL BZHAD PA'I RDO RJE RANG GI DRIN CAN MA RGAN BLO BZANG T'A RA ZHES BYA BAS LNGA PA'I LAM DU SONG TSE 'DIS MTSON PA'I BAR DO'I SEMS CAN RNAMS LA PHAN 'DOD KYI BSAM PAS, ^KUN GZIGS LNGA PA CHEN PO DANG, PAn CHEN THAMS CAD MKHYEN PA SOGS KYI LEGS BSHAD RNAMS LAS BTUS TE LAG TU BLANG BDE BAR, CHU PHO STAG LO'I DGUN ZLA 'BRING PO'I MKHA' 'GRO 'DU BA'I DUS BZANG LA AER TE NI JO BO'I LHA KHANG CHEN POR SBYAR BA'I YI GE PA NI BSOD NAMS DBANG PHYUG GO , ,,'DIS KYANG 'GRO BA MANG PO LA PHAN THOGS PAR GYUR CIG , , ,MANGGA LAm, ,)"
}