{
    "nlm_catalog": "M0058385-006",
    "input_file_number": "W1NLM472-I1N1M472",
    "language(s)_of_the_main_text_(үндсэн_хэл)": "Tibetan",
    "other_language(s)_in_the_main_text_(бусад_оролцсон_хэл)": "N",
    "full_title_(бүтэн_гарчиг)": "*, ,BLA MA LHA DANG CHOS SKYONG DREGS PA LCAM SRING LA BRTEN NAS SPYI DANG BYE BRAG GI DAM TSIG GSO BA'I PADMA KHA SBYOR GYI MAN NGAG BSGOM TSUL NYES KUN DAG BYED CES BYA BA BZHUGS SO, ,",
    "colophon_(төгсгөлийн_үг)": "@006B (CES BLA MA LHA DANG CHOS SKYONG DREGS PA LCAM SRING LA BRTEN NAS SPYI DANG BYE BRAG GI DAM TSIG GSO BA'I PADMA KHA SBYOR GYI MAN NGAG BSGOM TSUL NYES KUN DAG BYED CES BYA BA 'DI NI, ^BYANG PHYOGS BSTAN 'GRO'I GNYEN GCIG TU GYUR BA NGES DON GYI PAndI TA CHEN PO ^RJE BTZUN BLA MA RIN PO CHE YIL GOG SANG RDO RJE 'CHANG GI ZHAL SNGA NAS KYIS, 'DI LTA BU ZHIG BRTZOM DGOS ZHES PA'I BKA' SPYI BOR PHEBS PA DANG DU BLANGS TE, ^BTZUN GZUGS DHVA DZA'I MING CAN GYIS SBYAR BA'I YI GE PA NI DAD LDAN DGE SLONG NGAG DBANG BSTAN DAR GYIS BGYIS PA'O, ,'DI LA MA BSHAD LOG BSHAD LA SOGS PA'I NYES PA GANG YOD PA THAMS CAD BLA MA LHA BSRUNG DANG LUNG RIG NYAMS MYONG GI RTZAL DANG LDAN PA'I MKHAS PA RNAMS KYI SPYAN SNGAR MTHOL ZHING BSHAGS SO, ,DGE LEGS 'PHEL, ,)",
    "author_simple": "DHVA DZA'I MING CAN,",
    "cover_type_(хавтасны_төрөл)": "N/a",
    "condition_of_book_(номын_төлөв_байдал)": "Medium",
    "readability_of_book_(уншигдах_гаргацны_тухай)": "Good",
    "volume_(боть)": "N",
    "page_numbers_(хуудасны_дугаар)": "1A-6B",
    "size_of_printed_area_(дотоод_бичвэрийн_хэмжээ)": "32.5x9",
    "size_of_pages_(хуудасны_хэмжээ)": "41x10.5",
    "text_format_(бичвэрийн_төлөв)": "MS",
    "source": "National Library of Mongolia",
    "processing_history": [
        {
            "timestamp": "2024-09-14T05:41:35.527771+00:00",
            "processor": "MongoliaCatalogProcessor",
            "action": "created"
        }
    ]
}