{
    "nlm_catalog": "M0059090-011",
    "input_file_number": "W1NLM1177-I1NLM1177",
    "language(s)_of_the_main_text_(үндсэн_хэл)": "TIBETAN",
    "other_language(s)_in_the_main_text_(бусад_оролцсон_хэл)": "N",
    "full_title_(бүтэн_гарчиг)": "*, ,SKYABS 'GRO'I KHRID YIG BZHUGS SO, ,",
    "colophon_(төгсгөлийн_үг)": "@013A *, ,(CES PA 'DI NI RIGS RUS STOBS 'BYOR DANG 'DUN BRTZON PA PHUN SUM TSOGS PA'I HAR CHIN SKAL BZANG AE PHU DBANG GIS SKYABS 'GRO'I DMIGS RIM RGYAS SHING GO BDE BA CIG GYIS ZHES BSKUL BA LTAR BAN RGAN GYI NA BA NGAG DBANG BLO BZANG CHOS LDAN DPAL BZANG POS BOD CHOS LHA KHANG DU SBYAR BA'I YI GE PA NI SDOM BRTZON RNAM DPYOD YANGS PA'I DGE SLONG DPAL BZANG NGO, ,AOm SVASTI, THUB BSTAN DAR ZHING DE 'DZIN ZHABS BRTAN CHED, ,SAR 'DI BZHENGS PAS RGYU SBYOD GYIS GTZOS PA'I, ,'GRO KUN DKON MCHOG GSUM DANG MI 'BRAL ZHING, ,BLA MED RDZOGS PA'I BYANG CHUB MYUR THOB SHOG ,CES SKYABS KHRID KYI BAR 'DI NYID AE RTE NI PHYAG MDZOD PA DAM CHOS RAB RGYAS KYIS BZHENGS PA'I PAR BYANG DU 'DU GSUM PA ^BLO BZANG THUB BSTAN DBANG PHYUG 'JIGS MED RGYA MTSOS BRIS, ,SARBA MANGGA LAm, ,)",
    "author_simple": "NGAG DBANG BLO BZANG CHOS LDAN,",
    "cover_type_(хавтасны_төрөл)": "WOODEN BOX",
    "condition_of_book_(номын_төлөв_байдал)": "MEDIUM",
    "readability_of_book_(уншигдах_гаргацны_тухай)": "MEDIUM",
    "volume_(боть)": "N ",
    "page_numbers_(хуудасны_дугаар)": "1A-13A",
    "size_of_printed_area_(дотоод_бичвэрийн_хэмжээ)": "42x7",
    "size_of_pages_(хуудасны_хэмжээ)": "49x10",
    "text_format_(бичвэрийн_төлөв)": "XYL",
    "publisher_(хэвлэсэн_буюу_бүтээсэн_хийд_буюу_бархан)": "BOD CHOS LHA KHANG,",
    "source": "National Library of Mongolia",
    "processing_history": [
        {
            "timestamp": "2024-09-14T11:07:55.043716+00:00",
            "processor": "MongoliaCatalogProcessor",
            "action": "created"
        }
    ]
}