{
    "nlm_catalog": "M0058928-002",
    "input_file_number": "W1NLM1015-I1N1M1015",
    "language(s)_of_the_main_text_(үндсэн_хэл)": "Tibetan",
    "other_language(s)_in_the_main_text_(бусад_оролцсон_хэл)": "N",
    "full_title_(бүтэн_гарчиг)": "*, ,BLA MA MCHOD PA'I CHO GA DANG 'BREL PAR LAM GYI GTZO BO RNAM GSUM GYI ZAB KHRID SKYONG TSUL 'KHYER BDE BA LAM BZANG SNYING PO RAB GSAL ZHES BYA BA BZHUGS SO, ,",
    "author's_name_(_зохиогч)": "DAM TSIG RDO RJE,",
    "dates_of_the_author_(зохиогдсон_өдөр)": "",
    "translator_(орчуулагч)": "",
    "dates_of_the_translator_(орчуулагдсан_өдөр)": "",
    "editor_(хянан_тохиолдуулагч)": "",
    "dates_of_the_editor_(хянан_тохиолдуулсан_өдөр)": "",
    "year_of_this_edition_(дахин_засварлан_хэвлэсэн_өдөр)": "",
    "format_of_the_book_(номын_формат)": "",
    "cover_type_(хавтасны_төрөл)": "N/a",
    "condition_of_book_(номын_төлөв_байдал)": "Medium",
    "readability_of_book_(уншигдах_гаргацны_тухай)": "Good",
    "volume_(боть)": "N",
    "page_numbers_(хуудасны_дугаар)": "1A-19B",
    "size_of_printed_area_(дотоод_бичвэрийн_хэмжээ)": "46.5x6.5",
    "size_of_pages_(хуудасны_хэмжээ)": "53x9.5",
    "text_format_(бичвэрийн_төлөв)": "XYL",
    "publisher_(хэвлэсэн_буюу_бүтээсэн_хийд_буюу_бархан)": "",
    "copyright_owner_(зохиогчийн_эрхийг_эзэмшигч)": "",
    "location_of_printing_(хэвлэсэн_орон_нутаг)": "",
    "colophon_(төгсгөлийн_үг)": "@019A *, ,CES BLA MA'I RNAL 'BYOR DANG 'BREL PAR LAM GYI GTZO BO @020A *, ,RNAM GSUM GYI ZAB KHRID SKYONG TSUL 'KHYER BDE BA LAM BZANG SNYING PO RAB GSAL ZHES BYA BA 'DI NI, RANG GI SLOB MA DAD BRTZON RNAM DPYOD MCHOG TU DGE BA'I LHA BTZUN DGE BSKOS DGE SLONG RNAM RGYAL GRAGS PA DANG, CHOS LA 'DUN PA'I GUS LDAN DGE SLONG BLO BZANG TSANGS DBYANGS GNYIS KYIS 'DI LTA BU ZHIG DGOS ZHES BSKUL BA LTAR, MKHAS DANG GRUB PA'I DAM PA DU MA'I BKA' DRIN GYIS LEGS PAR 'TSO BA'I RGYAL KHAMS PA ^DAM TSIG RDO RJES 'KHRID YIG SNGA MA RNAMS LA GZHI BYAS, DPAL LDAN BLA MA DAM PA'I GSUNG RGYUN MAN NGAG GIS LEGS PAR BRGYAN TE, GNAD TSANG DON 'DUS KYI TSUL DU BKRA SHIS ZLA BA'I YAR TSES BZANG POR DGE LDAN DPAL RI'I DBEN GNAS SU SBYAR BA'I YI GE PA NI DPYOD LDAN SLOB BU SDOM BRTZON BSTAN 'DZIN BZANG PO'O, ,'DIS KYANG 'JAM MGON BSTAN PA'I SNYING PO RING DU GSAL BAR BYED NUS PA'I RGYUR GYUR CIG , ,,DZA YANTU, ,"
}