{
    "nlm_catalog": "M0066283-013",
    "input_file_number": "W1NLM8365-I1NLM8365",
    "language(s)_of_the_main_text_(үндсэн_хэл)": "TIBETAN",
    "other_language(s)_in_the_main_text_(бусад_оролцсон_хэл)": "N",
    "full_title_(бүтэн_гарчиг)": "*, ,DPAL MGON ZHAL BZHI PA BZLOG BSGYUR BZHUGS SO, ,",
    "colophon_(төгсгөлийн_үг)": "@003B (CES PA 'DI NI AER TE NI TAS CHEN SHES RAB RTZON GRUS DANG, ,DGE TSUL BTAN PA DAR RGYAS RNAMS BSKUL BA LA BRTEN NAS BSTAN PA'I GSAL BYED DZA YA PAndI TAS SBYAR BAS YI GE PA NI DGE LEGS RNAMS RGYAL RGYAL MTSAN NO, ,DGE LEGS 'PHEL BAR GYUR CIG ,)",
    "author_simple": "DZA YA PAndI TA,",
    "cover_type_(хавтасны_төрөл)": "N/A",
    "condition_of_book_(номын_төлөв_байдал)": "GOOD",
    "readability_of_book_(уншигдах_гаргацны_тухай)": "GOOD",
    "volume_(боть)": "N",
    "page_numbers_(хуудасны_дугаар)": "1A-3B",
    "size_of_printed_area_(дотоод_бичвэрийн_хэмжээ)": "26x8",
    "size_of_pages_(хуудасны_хэмжээ)": "31.5x9.5",
    "text_format_(бичвэрийн_төлөв)": "MS",
    "source": "National Library of Mongolia",
    "processing_history": [
        {
            "timestamp": "2024-09-14T16:45:40.473123+00:00",
            "processor": "MongoliaCatalogProcessor",
            "action": "created"
        }
    ]
}