{
    "nlm_catalog": "M0061170-006",
    "input_file_number": "W1NLM3252-I1NLM3252",
    "language(s)_of_the_main_text_(үндсэн_хэл)": "Tibetan",
    "other_language(s)_in_the_main_text_(бусад_оролцсон_хэл)": "N",
    "full_title_(бүтэн_гарчиг)": "*, ,KHRO BO SME BA BRTZEGS PA'I SGO NAS 'GONG BSREG BYA TSUL RAB 'JIGS RDO RJE'I ME LCE ZHES BYA BA BZHUGS SO, ,",
    "colophon_(төгсгөлийн_үг)": "@010A *, ,(ZHES PA 'DI'ANG BTZUN GZUGS NGAG DBANG RDO RJES, MKHAS GRUB GONG MA'I GSUNG GSANG LA 'BYIN BCUG CUNG ZAD BGYIS PA MANGGA LAm, ,)",
    "author_simple": "NGAG DBANG RDO RJE,",
    "cover_type_(хавтасны_төрөл)": "N/A",
    "condition_of_book_(номын_төлөв_байдал)": "GOOD",
    "readability_of_book_(уншигдах_гаргацны_тухай)": "GOOD",
    "volume_(боть)": "GA PA,",
    "page_numbers_(хуудасны_дугаар)": "1A-10A",
    "size_of_printed_area_(дотоод_бичвэрийн_хэмжээ)": "43.5x6",
    "size_of_pages_(хуудасны_хэмжээ)": "52.5x9.5",
    "text_format_(бичвэрийн_төлөв)": "XYL",
    "source": "National Library of Mongolia",
    "processing_history": [
        {
            "timestamp": "2024-09-14T02:32:20.870021+00:00",
            "processor": "MongoliaCatalogProcessor",
            "action": "created"
        }
    ]
}