{
    "nlm_catalog": "M0066101-028",
    "input_file_number": "W1NLM8183-I1NLM8183",
    "language(s)_of_the_main_text_(үндсэн_хэл)": "Tibetan",
    "other_language(s)_in_the_main_text_(бусад_оролцсон_хэл)": "N",
    "full_title_(бүтэн_гарчиг)": "*, ,DPAL GSANG BA'I BDAG PO PHYAG NA RDO RJE'I TSOGS MCHOD GSANG 'DZIN ROL BA'I DGA' STON CES BYA BA BZHUGS SO, ,",
    "colophon_(төгсгөлийн_үг)": "@006B (CES DPAL GSANG BA'I BDAG PO'I PHYAG NA RDO RJE BLA MED LUGS GANG LA'ANG SBYAR RUNG BA'I TSOGS MCHOD KYI CHO GA MDOR BSDUS BA GSANG 'DZIN DGYES PA'I DGA' STON ZHES BYA BA 'DI NI, LHAG PA'I LHA MCHOG 'DI LA YI DAM DU BYED PA'I DPYOD LDAN SLOB BU DGE TSUL BLO BZANG SHES RB KYIS BSKUL BA'I NGOR ^RGYAL KHAMS PA DAM TSIG RDO JES SUG BRIS SU BGYIS PA 'DIS KYANG BSTAN PA DANG SEMS CAN THAMS CAD LA PHAM PA RGYA CHEN PO 'BYUNG BAR GYUR CIG , ,,)",
    "author_simple": "DAM TSIG RDO RJE,",
    "cover_type_(хавтасны_төрөл)": "N/a",
    "condition_of_book_(номын_төлөв_байдал)": "Good",
    "readability_of_book_(уншигдах_гаргацны_тухай)": "Good",
    "volume_(боть)": "N",
    "page_numbers_(хуудасны_дугаар)": "1A-6B",
    "size_of_printed_area_(дотоод_бичвэрийн_хэмжээ)": "17.5x7",
    "size_of_pages_(хуудасны_хэмжээ)": "21.5x9.5",
    "text_format_(бичвэрийн_төлөв)": "MS",
    "source": "National Library of Mongolia",
    "processing_history": [
        {
            "timestamp": "2024-09-14T09:54:49.226172+00:00",
            "processor": "MongoliaCatalogProcessor",
            "action": "created"
        }
    ]
}