{
    "nlm_catalog": "M0062961-008",
    "input_file_number": "W1NLM5043-I1NLM5043",
    "language(s)_of_the_main_text_(үндсэн_хэл)": "TIBETAN",
    "other_language(s)_in_the_main_text_(бусад_оролцсон_хэл)": "N",
    "full_title_(бүтэн_гарчиг)": "*, ,DPAL RDO RJE 'JIGS BYED KYI RGYUD KYI RGYAL PO RTOG PA GSUM PA ZHES BYA BA BZHUGS SO, ,",
    "colophon_(төгсгөлийн_үг)": "@012A *, ,RGYA GAR GYI MKHAN PO AU YA MA DRA DANG, BOD KYI LOTZTSA BA RONG ZOM CHOS KYI BZANG POS BSGYUR TE GTAN LA PHAB PA'O, ,MANGGA LAm,, ,,",
    "cover_type_(хавтасны_төрөл)": "N/A",
    "condition_of_book_(номын_төлөв_байдал)": "GOOD",
    "readability_of_book_(уншигдах_гаргацны_тухай)": "GOOD",
    "volume_(боть)": "N",
    "page_numbers_(хуудасны_дугаар)": "1A-12A",
    "size_of_printed_area_(дотоод_бичвэрийн_хэмжээ)": "18x5.5",
    "size_of_pages_(хуудасны_хэмжээ)": "22.5x9",
    "text_format_(бичвэрийн_төлөв)": "XYL",
    "source": "National Library of Mongolia",
    "processing_history": [
        {
            "timestamp": "2024-09-14T13:52:38.527219+00:00",
            "processor": "MongoliaCatalogProcessor",
            "action": "created"
        }
    ]
}