{
    "nlm_catalog": "M0064904-008",
    "input_file_number": "W1NLM6986-I1NLM6986",
    "language(s)_of_the_main_text_(үндсэн_хэл)": "TIBETAN",
    "other_language(s)_in_the_main_text_(бусад_оролцсон_хэл)": "N",
    "full_title_(бүтэн_гарчиг)": "*, ,RI KHROD LA SA GYON MA'I SGO NAS BZLOG BSGYUR BYA TSUL NAD GDON KUN 'JOMS ZHES BYA BA BZHUGS SO, ,",
    "colophon_(төгсгөлийн_үг)": "@010B (CES RI KHROD LO MA GYON MA'I SGO NAS BZLOG BSGYUR BYA TSUL NAD 'DON KUN 'JOMS ZHES BYA BA 'DI NI, KHYAB BDAG RDO RJE CHANG CHEN PO ^`THU'U BKAN RIN PO CHE DHARMA BADZRA GYI BKA' 'BANGS THA SHAL PAn CHUNG, SNGAR BTZUN YE DPAL MING CANG GYIS MI 'DOD RKYEN NGAN GYIS MNAR PA'I SEMS CAN RNAMS LA PHAN PAR BSAM NAS, GSER GYIS SKU RAGS ZHES PA'I SA CHAR YIG THE 'TU PA BGYIS PA'O, ,'DI NI DAD LDAN GU SHRI T'A BLA MA BSHAD BSGRUB BSTAN PA'I 'BYUNG GNAS, PAR DU BSGRUB PA 'DIS KYANG TSE BSOD DPAL @011A *, ,'BYOR LEGS TSOGS THAMS CAD RGYAS PA DANG, BSAM DON THAMS CAD YID BZHIN DU 'GRUB PAR GYUR CIG ,DGE'O, ,LEGS SO BKRA SHIS PAR GYUR CIG , ,,)",
    "author_simple": "YE DPAL MING CANG,",
    "cover_type_(хавтасны_төрөл)": "paper cover",
    "condition_of_book_(номын_төлөв_байдал)": "GOOD",
    "readability_of_book_(уншигдах_гаргацны_тухай)": "GOOD",
    "volume_(боть)": "N",
    "page_numbers_(хуудасны_дугаар)": "1A-11A",
    "size_of_printed_area_(дотоод_бичвэрийн_хэмжээ)": "17x7",
    "size_of_pages_(хуудасны_хэмжээ)": "22x9",
    "text_format_(бичвэрийн_төлөв)": "MS",
    "source": "National Library of Mongolia",
    "processing_history": [
        {
            "timestamp": "2024-09-14T15:12:52.406394+00:00",
            "processor": "MongoliaCatalogProcessor",
            "action": "created"
        }
    ]
}