{
    "nlm_catalog": "M0067321-024",
    "input_file_number": "W1NLM9403-I1NLM9403",
    "language(s)_of_the_main_text_(үндсэн_хэл)": "Tibetan",
    "other_language(s)_in_the_main_text_(бусад_оролцсон_хэл)": "N",
    "full_title_(бүтэн_гарчиг)": "*, ,SGROL DKAR GYI SGO NAS TSE SGRUB BYA TSUL BZHUGS, ,",
    "colophon_(төгсгөлийн_үг)": "@008A *, ,(ZHES SGROL MA DKAR MO LA BRTEN NAS TSE @008B SGRUB PA'I CHO GA 'CHI MED BDUD RTZI'I BUM BZANG ZHES BYA BA 'DI NI, DKA' BCU NGAG DBANG BLO GTER GYIS BSKUL NGOR, ^BTZUN PA DKON MCHOG 'JIGS MED DBANG POS CHOS SDE CHEN PO SKU 'BUM DU SBYAR BA'O,,)",
    "author_simple": "DKON MCHOG 'JIGS MED DBANG PO,",
    "cover_type_(хавтасны_төрөл)": "N/a",
    "condition_of_book_(номын_төлөв_байдал)": "Good",
    "readability_of_book_(уншигдах_гаргацны_тухай)": "Good",
    "volume_(боть)": "N",
    "page_numbers_(хуудасны_дугаар)": "1A-8B",
    "size_of_printed_area_(дотоод_бичвэрийн_хэмжээ)": "23.5x6",
    "size_of_pages_(хуудасны_хэмжээ)": "27x8.5",
    "text_format_(бичвэрийн_төлөв)": "XYL",
    "source": "National Library of Mongolia",
    "processing_history": [
        {
            "timestamp": "2024-09-14T11:02:33.028810+00:00",
            "processor": "MongoliaCatalogProcessor",
            "action": "created"
        }
    ]
}