{
    "nlm_catalog": "M0066190-001",
    "input_file_number": "W1NLM8272-I1NLM8272",
    "language(s)_of_the_main_text_(үндсэн_хэл)": "TIBETAN",
    "other_language(s)_in_the_main_text_(бусад_оролцсон_хэл)": "N",
    "full_title_(бүтэн_гарчиг)": "*, ,PHUG LUGS RTZIS KYI LEGS BSHAD MKHAS PA'I MGUL RGYAN BEEd'UR DKAR PO'I DO SHAL DPYOD LDAN SNYING NOR LAS BAG RTZIS BZHUGS SO, ,",
    "author's_name_(_зохиогч)": "",
    "dates_of_the_author_(зохиогдсон_өдөр)": "",
    "translator_(орчуулагч)": "",
    "dates_of_the_translator_(орчуулагдсан_өдөр)": "",
    "editor_(хянан_тохиолдуулагч)": "",
    "dates_of_the_editor_(хянан_тохиолдуулсан_өдөр)": "",
    "year_of_this_edition_(дахин_засварлан_хэвлэсэн_өдөр)": "",
    "format_of_the_book_(номын_формат)": "",
    "cover_type_(хавтасны_төрөл)": "N/A",
    "condition_of_book_(номын_төлөв_байдал)": "GOOD",
    "readability_of_book_(уншигдах_гаргацны_тухай)": "GOOD",
    "volume_(боть)": "N",
    "page_numbers_(хуудасны_дугаар)": "1A-36A",
    "size_of_printed_area_(дотоод_бичвэрийн_хэмжээ)": "30x7",
    "size_of_pages_(хуудасны_хэмжээ)": "34x8.5",
    "text_format_(бичвэрийн_төлөв)": "MS",
    "publisher_(хэвлэсэн_буюу_бүтээсэн_хийд_буюу_бархан)": "",
    "copyright_owner_(зохиогчийн_эрхийг_эзэмшигч)": "",
    "location_of_printing_(хэвлэсэн_орон_нутаг)": "",
    "colophon_(төгсгөлийн_үг)": "@035B (CES PHUG LUGS RTZIS KYI LEGS BSHAD MKHAS PA'I MGUL RGYAN BEEd'UR DKAR PO'I DO SHAL DPYOD LDAN SNYING NOR LAS, ,BAG RTZIS 'DI 'GYUR 'GO RE RER MA ZAD PHYIS KYING MKHAS PA RES BAG RTZIS RE MDZAD PA'I MING GI RNAM GRANGS MI GCIG SHIN TU MANG BA DANG, ,DON YANG MI GCIG PA NYI SHU LHAG MTHONG BAR BYUNG BA RNAMS KYI 'BRAS BU DANG BCOS SOGS BOD DU BYAS PA'I BSTAN BCOS KYI RIGS RGYUD KYI GO BA LON MIN SNA TSOGS RNAMS KYANG TSANG MA 'DIN BAG RTZIS RENG DU PUSTA KA GCIG TU BCAD RUNG MKHA DBANG DPAL MGON 'PHRIN LAS PA'I BDE LEGS KUN 'BYUNG LA GZHI BCOL DE NYID LA YANG BYUR THAG NYI SHU SOGS DKRUGS PA DANG SPAS PA'I MTSANG BA RNAMS RTZA 'GREL DANG 'GYUR 'GO GZHAN GYI RGYUD NAS KHA BKANG, ,GZHAN YANG RGYA PHRUG DKON RIN GYI RIN CHEN KUN DUS, ,SPUG STON GYI RGYUD LUNG KUN DUS, ,SNYAN GROD PA'I DPAG BSAM LJON SHING, DE'I GSAL BYED SHUN WAGS 'GREL PA LJON SHING MDZES RGYAN GSAL BA'I ME LONG RIN CHEN 'PHRENG BA RNAMS @036A *, ,NAS MGAL CHAR MI 'GRO BA'I RIGS KYI LEGS CHA DU MA NAS BRGYAN TE BGYIS PA RNAMS BRTZI DUS MA LUS KHYAD RDEL GRANGS SU BSGRIGS PAS DON TSAN YAS MAS SU 'THOR BA RNAMS SO SO'I SDE TSAN DU BSGRIL BA'I SA DPYAD GSUM DU BSDUS, ,RIN CHEN SPUNGS PA NAS BSHAD PA'I KHAM YU ROG MO DANG 'BYUNG BA RIN CHEN KUN 'DUS NAS GSUNGS PA'I KHRI SGO BCU GNYIS RNAMS SO SOR GSIL NA ZIL CHES PAS RANG TSAN DU BZHAG STE BGYIS PA'I LE'U STE NYER GSUM PA'O, ,BKRA SHIS PAR GYUR CIG ,MANGGA LAM, ,)",
    "cataloger-gerelmaa": null
}