{
    "nlm_catalog": "M0067726-008",
    "input_file_number": "W1NLM9808-I1NLM9808",
    "other_language(s)_in_the_main_text_(бусад_оролцсон_хэл)": "N",
    "full_title_(бүтэн_гарчиг)": "*, ,RGYAL PO CHEN PO RNAM THOS SRAS LA BRTEN NAS RGYAS PA GTZO BOR GYUR BA'I 'JAM PO GSUM GYI SREG BYED TSUL YID BZHIN DBANG RGYAL ZHES BYA BA BZHUGS SO, ,",
    "colophon_(төгсгөлийн_үг)": "@013B (CES RGYAL PO CHEN PO RNAM THOS SRAS LA BRTEN NAS RGYAS PA GTZO BOR GYUR PA'I 'JAM PO GSUM GYI SBYIN SREG BYED TSUL YID BZHIN DBANG RGYAL ZHES BYA 'DI NI RONG PO'I DGON PA BDE CHEN CHOS 'KHOR GLING GI GRVA TSANG GSUM GYI YAL GYAL DPAL LDAN DUS KYI 'KHOR LO'I GRVA TSANG GI BLA MA DGE 'DUN 'DUS SPYI NAS LHA DAR S'URYA'I MDANGS LDAN DANG BCAS TE BSKUL BA'I NGOR ^SH'AKYA'I BTZUN PA BLO BZANG RGYAL MTSAN SENGGES RJE YAB SRAS KYI GSUNG RAB KYI DGONGS PA BZHIN DU RANG LO DGU BCUR SON PAR BYUNG BCU BZHI'I ME RTA'I HOR ZLA BCU GCIG PA'I GA-YUL LAS RNAM PAR RGYAL BA'I YAR NGO'I SKAR MA RGYAL GYI NYIN GRUB DBANG SKAL LDAN RGYA MTSO'I GDAN SA DE NYID NAS SBYAR BA'I RTZA BA'I YI GE PA NI MDZOD PA CHOS RJE'I TSA BA BSTAN PA RGYAL MTSAN GYIS BGYIS SHING SLAR SHOG BUR 'BEBS PA PO NI DGE SLONG 'JAM DBYANGS BDE CHEN GYIS BYAS PA 'JIG RTEN KUN TU SHIS PAR GYUR CIG DZA YANTU,, BKRA SHIS 'BAR GYUR CIG , ,,)",
    "author_simple": "BLO BZANG RGYAL MTSAN SENGGE, ",
    "dates_of_the_author_(зохиогдсон_өдөр)": "RAB BYUNG BCU BZHI'I ME RTA'I HOR ZLA BCU GCIG PA'I GA-YUL LAS RNAM PAR RGYAL BA'I YAR NGO'I SKAR MA RGYAL GYI NYIN,",
    "cover_type_(хавтасны_төрөл)": "N/A",
    "condition_of_book_(номын_төлөв_байдал)": "GOOD",
    "readability_of_book_(уншигдах_гаргацны_тухай)": "GOOD",
    "volume_(боть)": "N",
    "page_numbers_(хуудасны_дугаар)": "1A-13B",
    "size_of_printed_area_(дотоод_бичвэрийн_хэмжээ)": "30x7.5",
    "size_of_pages_(хуудасны_хэмжээ)": "35.5x9",
    "text_format_(бичвэрийн_төлөв)": "MS",
    "source": "National Library of Mongolia",
    "processing_history": [
        {
            "timestamp": "2025-03-11T23:22:32.004072+00:00",
            "processor": "MongoliaCatalogProcessor",
            "action": "created"
        }
    ]
}