{
    "nlm_catalog": "M0061491-001",
    "input_file_number": "W1NLM3573-I1NLM3573",
    "language(s)_of_the_main_text_(үндсэн_хэл)": "Tibetan",
    "other_language(s)_in_the_main_text_(бусад_оролцсон_хэл)": "N",
    "full_title_(бүтэн_гарчиг)": "*, ,LAS DANG PO NYE BAR MKHO BA'I BYANG CHUB TU BGROD PA'I BDE LAM ZHES BYA BA BZHUGS SO, ,",
    "colophon_(төгсгөлийн_үг)": "@128B GONG CES PAn CHEN THAMS CAD MKHYEN PA BLO BZANG CHOS KYI RGYAL MTSAN GYI THUGS SRAS DAM PA SNGAGS CHEN RDO RJE 'DZIN PA DKON MCHOG RGYAL MTSAN GYIS MDZAD PA'I BYANG CHUB LAM RIM 'DI NYID DON 'DUS SHING 'KHYER BDE BA DANG, BYIN RLABS KYI TSAN KHA SHIN TU CHE BAS DON GNYER CAN LA PHAN PAR BSAMS TE, LAM 'DIR MOS PA'I MDZOD PA DGE SLONG BLO BZANG CHOS 'PHEL @128A 'OG *, ,GYIS SPAR DU BSGRUB PA'I TSE, SPAR BYANG DGOS TSUL MOL BA LTAR, SDE SNOD 'DZIN PA LCANG SKYA ROL PA'I RDO RJES BRIS PA DGE LEGS SU GYUR CIG , ,,",
    "cover_type_(хавтасны_төрөл)": "N/A",
    "condition_of_book_(номын_төлөв_байдал)": "GOOD",
    "readability_of_book_(уншигдах_гаргацны_тухай)": "GOOD",
    "volume_(боть)": "N",
    "page_numbers_(хуудасны_дугаар)": "1A-128A GONG, 'OG",
    "size_of_printed_area_(дотоод_бичвэрийн_хэмжээ)": "19x4.5",
    "size_of_pages_(хуудасны_хэмжээ)": "23.5x7",
    "text_format_(бичвэрийн_төлөв)": "XYL",
    "source": "National Library of Mongolia",
    "processing_history": [
        {
            "timestamp": "2024-09-14T02:42:30.106156+00:00",
            "processor": "MongoliaCatalogProcessor",
            "action": "created"
        }
    ]
}