{
    "nlm_catalog": "M0067499-031",
    "input_file_number": "W1NLM9581-I1NLM9581",
    "other_language(s)_in_the_main_text_(бусад_оролцсон_хэл)": "N",
    "full_title_(бүтэн_гарчиг)": "*, ,MKHA' SPYOD MA'I TSOGS 'KHOR BDE CHEN DBYINGS SU ROL PA'I DGA' STON ZHES BYA BA BZHUGS SO, ,",
    "colophon_(төгсгөлийн_үг)": "@007B (ZHES RDO RJE RNAL 'BYOR MA LA TSOGS MCHOD 'BUL TSUL BDE CHEN DBYANGS SU ROL PA'I DGA' STON ZHES BYA BA 'DI NI, SPRUL PA'I SKU DKON MCHOG RIG 'DZIN DPAL MOS BSKUL NGOR ^BHU SU KU BA RIN CHEN RDO RJES SNRON ZLA BA'I YAR NGO'I TSES BCUR RANG GSHAGS AE WAm DU SBYAR BA'I YI GE PA NI ZHABS DRUNG SHI LAS BGYIS PA DZA YANTU, BAR 'DI KUN MKHYEN 'JAM DBYANGS BZHAD PA'I SDE'I, ,GDAN SA CHEN PO BKRA SHIS 'KHYIL GLING NAS, ,THUB DBANG BSTAN PA'I NYI MA STONG PHRAG GI ,GANTA LA DU LHAG BSAM DAG PAS BSGRUBS, ,MANGGA LAm, ,)",
    "author_simple": "RIN CHEN RDO RJE, ",
    "dates_of_the_author_(зохиогдсон_өдөр)": "SNRON ZLA BA'I YAR NGO'I TSES BCU,",
    "cover_type_(хавтасны_төрөл)": "N/A",
    "condition_of_book_(номын_төлөв_байдал)": "GOOD",
    "readability_of_book_(уншигдах_гаргацны_тухай)": "GOOD",
    "volume_(боть)": "N",
    "page_numbers_(хуудасны_дугаар)": "5A-7B",
    "size_of_printed_area_(дотоод_бичвэрийн_хэмжээ)": "19x7",
    "size_of_pages_(хуудасны_хэмжээ)": "22.5x9",
    "text_format_(бичвэрийн_төлөв)": "MS",
    "publisher_(хэвлэсэн_буюу_бүтээсэн_хийд_буюу_бархан)": "AE WAm, BKRA SHIS 'KHYIL GLING ,",
    "source": "National Library of Mongolia",
    "processing_history": [
        {
            "timestamp": "2025-03-12T00:05:20.703205+00:00",
            "processor": "MongoliaCatalogProcessor",
            "action": "created"
        }
    ]
}