{
    "nlm_catalog": "M0065432-004",
    "input_file_number": "W1NLM7514-I1NLM7514",
    "language(s)_of_the_main_text_(үндсэн_хэл)": "TIBETAN",
    "other_language(s)_in_the_main_text_(бусад_оролцсон_хэл)": "N",
    "full_title_(бүтэн_гарчиг)": "*, ,DMAR SNYUNG SPRUL SKU LA GNANG BA'I BSLAB BYA BZHUGS SO, ,",
    "colophon_(төгсгөлийн_үг)": "@018B (ZHES PA 'DI NI DAM PA'I YON TAN GYIS MDZES PA'I DMAR SNYUNG MKHAN PO SPRUL PA'I SKU BLO BZANG LEGS BSHAD RGYA MTSO NAS SOG YUL DU 'BYON DGOS BYUNG TSE 'GRO 'DUG SPYOD LAM TZAM GYI BSLAB BYA DGOS TSUL NAN TAN MDZAD NGOR ^RATNA DHVA DZAS BKRA SHIS 'KHYIL GYI SPYIL CHUNG BSAM 'GRUB DGA' BDE'I TSAL NAS BRIS PA'I YI GE PA NI DGE SLONG DKON MCHOG MKHYEN RAB KYIS BGYIS PA @019A *, ,'DI YI DGE BAS SRAS BCAS RGYAL BA'I THUGS BZHED MTHA' DAG 'GRO BA YONGS LA LHUN GYIS GRUB PAR GYUR CIG , ,,CHOS SBYIN RGYA CHER SPEL PHYIR CHOS GRVA CHEN PO DGA' LDAN CHOS 'KHOR GLING NAS PAR DU BSGRUBS, SARBA BANDA AUTDZA YANTU, ,SARBA MANGGA LAm,, ,,)",
    "author_simple": "DKON MCHOG RGYAL MTSAN,",
    "cover_type_(хавтасны_төрөл)": "N/A",
    "condition_of_book_(номын_төлөв_байдал)": "GOOD",
    "readability_of_book_(уншигдах_гаргацны_тухай)": "GOOD",
    "volume_(боть)": "N",
    "page_numbers_(хуудасны_дугаар)": "14B-19A",
    "size_of_printed_area_(дотоод_бичвэрийн_хэмжээ)": "44x6.5",
    "size_of_pages_(хуудасны_хэмжээ)": "52.5x9.5",
    "text_format_(бичвэрийн_төлөв)": "XYL",
    "source": "National Library of Mongolia",
    "processing_history": [
        {
            "timestamp": "2024-09-14T15:34:02.886470+00:00",
            "processor": "MongoliaCatalogProcessor",
            "action": "created"
        }
    ]
}