{
    "nlm_catalog": "M0062926-083",
    "input_file_number": "W1NLM5008-I1NLM5008",
    "language(s)_of_the_main_text_(үндсэн_хэл)": "Tibetan",
    "other_language(s)_in_the_main_text_(бусад_оролцсон_хэл)": "N",
    "full_title_(бүтэн_гарчиг)": "*, ,RJE BTZUN RDO RJE RNAL 'BYOR MA'I BSNYEN SGRUB KYI RIM PA GSAL BAR BSHAD PA GSANG CHEN BCUD KYI THIG PA ZHES BYA BA BZHUGS SO, ,",
    "colophon_(төгсгөлийн_үг)": "@016A *, ,(CES RNAL 'BYOR MA N'A RO MKHA' SPYOD DU GRAGS PA'I BSNYEN SGRUB KYI RIM PA GSAL BAR BSHAD PA GSANG CHEN BCUD KYI THIG PA ZHES BYA BA 'DI NI BSTAN PA'I GSAL BYED DAM PA THU'U BKVAN SPRUL SKU RIN PO CHE ^ BLO BZANG CHOS KYI NYI MA DPAL BZANG POS GSER GYI MAndAL DANG BCAS YANG YANG NAN TAN DU BSKUL BA DON YOD PAR BYA BA'I PHYIR DU RDO RJE 'CHANG DANG MI GNYIS PA'I BLA MA DAM PA DU MA'I ZHABS LA GDUGS PA'I BKA' DRIN GYIS MDO RGYUD MTHA' DAG GO DON LA RIGS PA'I RDO RJES, STOBS KYI 'KHOR LOS BSGYUR BA ^ 'JAM DBYANGS GONG MA CHEN PO'I PHO BRANG GI NYE 'DABS BKA' DANG BSTAN BCOS 'GYUR RO COG GI TSAL DGON GNAS BKRA SHIS RAB RGYAS KYI RANG BSHAG BDE CHEN GAN MDZOD DU SBYAR BA'I YI GE PA NI RANG GI NYE GNAS DAD BRTZON RNAM DPYOD MCHOG TU YANGS SHING LA MA 'DI LA MOS PA LHUR LEN PA DGE SLONG DGE LEGS NAM MKHAS BGYIS PA @016B 'DIS KYANG BLO BZANG RGYAL BA SPYI DANG KHYAD PAR GSANG CHEN THIG PA'I LAM BZANG PHYOGS DUS THAMS CAD DU RGYAS PAR GYUR CIG , ,,DPE 'DI SNOD MIN LA SHIN TU GSANG BAR BYA BA KHO NA YIN PAS GAR THOD DU MI STON PAR THUGS LA BANGN 'TSAL, ,DGE'O, ,)",
    "author_simple": "BLO BZANG CHOS KYI NYI MA,",
    "cover_type_(хавтасны_төрөл)": "N/a",
    "condition_of_book_(номын_төлөв_байдал)": "Good",
    "readability_of_book_(уншигдах_гаргацны_тухай)": "Good",
    "volume_(боть)": "N",
    "page_numbers_(хуудасны_дугаар)": "1A-16B",
    "size_of_printed_area_(дотоод_бичвэрийн_хэмжээ)": "29x9",
    "size_of_pages_(хуудасны_хэмжээ)": "35x11",
    "text_format_(бичвэрийн_төлөв)": "MS",
    "source": "National Library of Mongolia",
    "processing_history": [
        {
            "timestamp": "2024-09-14T07:25:33.157915+00:00",
            "processor": "MongoliaCatalogProcessor",
            "action": "created"
        }
    ]
}