{
    "nlm_catalog": "M0066217-012",
    "input_file_number": "W1NLM8299-I1NLM8299",
    "language(s)_of_the_main_text_(үндсэн_хэл)": "TIBETAN",
    "other_language(s)_in_the_main_text_(бусад_оролцсон_хэл)": "N",
    "full_title_(бүтэн_гарчиг)": "*, ,'GO BA'I LHA LNGA 'KHOR DANG BCAS PA LA RTEN PA'I SGO NAS BCOL GYI BZLOG BSGYUR BYED TSUL PHAS RGOL MTHA' DAG 'JOMS PA'I MTSON CHA'I BZHUGS SO, ,",
    "colophon_(төгсгөлийн_үг)": "@010A *, ,(CES 'GO BA'I LHA LNGA'I BZLOG PA'I CHO GA 'DI NI RATNA SIDDHI'I PHAN PA'I SLAD DU GRUB THOB RVA SGRENGS RDO RJE 'CHANG GIS SBYAR BA'I YI GE PA NI BIKshU SU MA TI BRIS PA'O, ,DGE'O, ,)",
    "author_simple": "RDO RJE 'CHANG,",
    "cover_type_(хавтасны_төрөл)": "N/A",
    "condition_of_book_(номын_төлөв_байдал)": "GOOD",
    "readability_of_book_(уншигдах_гаргацны_тухай)": "GOOD",
    "volume_(боть)": "N",
    "page_numbers_(хуудасны_дугаар)": "1A-10A",
    "size_of_printed_area_(дотоод_бичвэрийн_хэмжээ)": "31x6.5",
    "size_of_pages_(хуудасны_хэмжээ)": "34x8",
    "text_format_(бичвэрийн_төлөв)": "MS",
    "source": "National Library of Mongolia",
    "processing_history": [
        {
            "timestamp": "2024-09-14T16:37:57.208937+00:00",
            "processor": "MongoliaCatalogProcessor",
            "action": "created"
        }
    ]
}