{
    "nlm_catalog": "M0065100-047",
    "input_file_number": "W1NLM7182-I1NLM7182",
    "language(s)_of_the_main_text_(үндсэн_хэл)": "TIBETAN",
    "other_language(s)_in_the_main_text_(бусад_оролцсон_хэл)": "N",
    "full_title_(бүтэн_гарчиг)": "*, ,CHOS GRVA CHEN PO DPAL ZHA LU RI MTHIL GYI BSTAN PA'I SROG SHING NI, ",
    "colophon_(төгсгөлийн_үг)": "@044B ZHES PA 'DI YANG DPAL ZHA LU'I CHOS GRVA CHEN POR, MA HE MCHOD PA'I DUS SU, CHOS KYI RGYAL PO YAB YUM GYI ZHAL 'BAG BYIN RLABS CHE ZHING SHIN TU GNYAN PA LA BKA' BSGO DAM BZHAG BYAS PA'I TSE, ZHAL 'BAG GNYIS KYI DBU THOG HU RDO RJE BZHAG STE, RANG GI BLO NAS GANG THON BYAS PA DE NYID CHOS GRVA CHEN PO LA ZHA LU RI MTHIL GYI BSTAN PA'I SROG SHING ,RIN PO CHE CHOS KYI RJE RIN CHEN BSOD NAMS MCHOG GRUB KYIS YI GER 'GOD DGOS ZHES NAN GYIS BSKUL BA LA BRTEN NAS, GSHIN RJE'I GSHED KYI RNAL 'BYOR PA BLO BZANG CHOS KYI RGYAL MTSAN GYIS, DPAL ZHA LU'I BLA BRANG DU BRIS PA'I YI GE PA NI, DGE TSUL RNAM DPYOD DANG LDAN PA BLO BZANG DBANG RGYAL LO,, ,,",
    "author_simple": "BLO BZANG CHOS KYI RGYAL MTSAN, ",
    "cover_type_(хавтасны_төрөл)": "N/A",
    "condition_of_book_(номын_төлөв_байдал)": "GOOD",
    "readability_of_book_(уншигдах_гаргацны_тухай)": "GOOD",
    "volume_(боть)": "HI PA,",
    "page_numbers_(хуудасны_дугаар)": "43A-45A",
    "size_of_printed_area_(дотоод_бичвэрийн_хэмжээ)": "51x7",
    "size_of_pages_(хуудасны_хэмжээ)": "62x10.5",
    "text_format_(бичвэрийн_төлөв)": "XYL",
    "source": "National Library of Mongolia",
    "processing_history": [
        {
            "timestamp": "2024-09-14T15:23:24.823261+00:00",
            "processor": "MongoliaCatalogProcessor",
            "action": "created"
        }
    ]
}