{
    "nlm_catalog": "M0066241-019",
    "input_file_number": "W1NLM8323-I1NLM8323",
    "language(s)_of_the_main_text_(үндсэн_хэл)": "Tibetan",
    "other_language(s)_in_the_main_text_(бусад_оролцсон_хэл)": "N",
    "full_title_(бүтэн_гарчиг)": "*, ,'BRUM NAD SOGS RIMS NAD ZHI ZHING YANG PA'I PHYIR SNA TSOGS YUM GYI MAndAL BZHI PA, 'BRUM PA YANG ZHING DKAR POR 'GYUR BA'I MAN NGAG SNA TSOGS YUM DANG 'BREL NAS BYA TSUL BDUD RTZI BUM BZANG RDO RJE'I TSER MA ZHI BYED BZHUGS SO, ,",
    "colophon_(төгсгөлийн_үг)": "@008A *, ,MI BSKYOD RDO RJES SBYAR BA'O,, ,,",
    "author_simple": "MI BSKYOD RDO RJE,",
    "cover_type_(хавтасны_төрөл)": "N/a",
    "condition_of_book_(номын_төлөв_байдал)": "Good",
    "readability_of_book_(уншигдах_гаргацны_тухай)": "Good",
    "volume_(боть)": "N",
    "page_numbers_(хуудасны_дугаар)": "1A-8A",
    "size_of_printed_area_(дотоод_бичвэрийн_хэмжээ)": "17.5x8",
    "size_of_pages_(хуудасны_хэмжээ)": "22.5x9",
    "text_format_(бичвэрийн_төлөв)": "MS",
    "source": "National Library of Mongolia",
    "processing_history": [
        {
            "timestamp": "2024-09-14T10:07:44.079012+00:00",
            "processor": "MongoliaCatalogProcessor",
            "action": "created"
        }
    ]
}