{
    "nlm_catalog": "M0064087-006",
    "input_file_number": "W1NLM6169-I1NLM6169",
    "language(s)_of_the_main_text_(үндсэн_хэл)": "TIBETAN",
    "other_language(s)_in_the_main_text_(бусад_оролцсон_хэл)": "N",
    "full_title_(бүтэн_гарчиг)": "*, ,ZAB LAM BLA MA'I RNAL 'BYOR DGA' LDAN LHA BRGYA MA LA BRTEN NAS MDO SNGAGS KYI LAM CHA TSANG BAR NYAMS SU LEN TSUL GYI MAN NGAG SKAL BZANG DGA' STON ZHES BYA BA BZHUGS SO, ,",
    "author's_name_(_зохиогч)": "DBYANGS CAN GRUB PA'I RDO RJE,",
    "dates_of_the_author_(зохиогдсон_өдөр)": "",
    "translator_(орчуулагч)": "",
    "dates_of_the_translator_(орчуулагдсан_өдөр)": "",
    "editor_(хянан_тохиолдуулагч)": "",
    "dates_of_the_editor_(хянан_тохиолдуулсан_өдөр)": "",
    "year_of_this_edition_(дахин_засварлан_хэвлэсэн_өдөр)": "",
    "format_of_the_book_(номын_формат)": "",
    "cover_type_(хавтасны_төрөл)": "N/A",
    "condition_of_book_(номын_төлөв_байдал)": "GOOD",
    "readability_of_book_(уншигдах_гаргацны_тухай)": "GOOD",
    "volume_(боть)": "N",
    "page_numbers_(хуудасны_дугаар)": "1A-19B",
    "size_of_printed_area_(дотоод_бичвэрийн_хэмжээ)": "40x6.5",
    "size_of_pages_(хуудасны_хэмжээ)": "45x9",
    "text_format_(бичвэрийн_төлөв)": "MS",
    "publisher_(хэвлэсэн_буюу_бүтээсэн_хийд_буюу_бархан)": "",
    "copyright_owner_(зохиогчийн_эрхийг_эзэмшигч)": "",
    "location_of_printing_(хэвлэсэн_орон_нутаг)": "",
    "colophon_(төгсгөлийн_үг)": "@019A *, ,(CES ZAB LAM BLA MA'I RNAL 'BYOR DGA' LDAN LHA RGYA MA LA BRTEN NAS MDO SNGAGS KYI LAM CHA TSANG BAR NYAMS SU LEN TSUL GYI MAN NGAG SKAL BZANG DGA' STON ZHES BYA BA 'DI NI, SPYI RNYING DRUNG RAM PA DPAL LDAN DON GRUB NAS 'DI LTA BU ZHIG @019B GYIS SHIG CES RTEN DANG BCAS NAN BSKUL MDZAD PAR BRTEN 'DI SKOR GYI GZHUNG MANG POR LEGS PAR BRTAGS NAS 'JAM PA'I DBYANGS GUNG THANG RIN PO CHE DKON MCHOG BSTAN PA'I SGRON MES MDZAD PA'I GZHUNG LA GZHI BYAS 'KHRID CHEN BZHI'I SKOR DANG, SNGAGS PA ZLA TSUL, 'PHO BA'I RNAL 'BYOR BA SNGO SMON SOGS LAS DANG PO BA LA GAL CHE BA RNAMS RGYAL MCHOG BSKAL BZANG RGYA MTSO DANG BLA MA'I MAN NGAG GIS KHA BSKANGS TE THAMS CAD MKHYEN PA DHARMA BHA DRA DPAL BZANG PO'I BKA' DRIN LAS GDAMS PA 'DI NYID KYI RGYUN LEGS PAR THOB PA'I GTZUN GZIGS DBYANGS CAN GRUB PA'I RDO RJER 'BOD PAS, ZAD PA ZHES PA ME STAG LO'I DBO ZLA BA'I DKAR PHYOGS BZANG PO GNYIS PAR BZHAD DNGUL CHU RI KHROD DGA' LDAN RTZE'I GZIM PHUG TU GRUB PAR BGYIS PA SARBA DIKshU YA BA PUshnA NTU,, ,,",
    "cataloger-gerelmaa": null
}