{
    "nlm_catalog": "M0066963-032",
    "input_file_number": "W1NLM9045-I1NLM9045",
    "language(s)_of_the_main_text_(үндсэн_хэл)": "Tibetan",
    "other_language(s)_in_the_main_text_(бусад_оролцсон_хэл)": "N",
    "full_title_(бүтэн_гарчиг)": "*, ,DPAL RDO RJE 'JIGS BYED KYI SGO NAS LHO SGO GIS CHO GA BYA BA'I TSUL BZHUGS SO, ,",
    "colophon_(төгсгөлийн_үг)": "@014B (CES DPAL RDO RJE 'JIGS BYED LHA BCU GSUM GYI DKYIL 'KHOR LA BRTEN NAS SPYANG CHOG BYA BA'I TSUL 'DI NI RANG NYID RTAN PA GSO BA DANG, DON GNYER CAN GZHAN MANG POS KYANG BSKUL BA LA BRTEN NAS, DGE SLONG YE SHES RGYAL MTSAN GYIS BKRA SHIS BSAM GTAN GLING DU SBYAR BA'O, ,'DIS KYANG 'GRO BA MANG PO LA PHAN PAR GYUR CIG , ,,)",
    "author_simple": "YE SHES RGYAL MTSAN,",
    "cover_type_(хавтасны_төрөл)": "N/a",
    "condition_of_book_(номын_төлөв_байдал)": "Good",
    "readability_of_book_(уншигдах_гаргацны_тухай)": "Good",
    "volume_(боть)": "N",
    "page_numbers_(хуудасны_дугаар)": "1A-14B",
    "size_of_printed_area_(дотоод_бичвэрийн_хэмжээ)": "31x8",
    "size_of_pages_(хуудасны_хэмжээ)": "44.5x8.5",
    "text_format_(бичвэрийн_төлөв)": "MS",
    "source": "National Library of Mongolia",
    "processing_history": [
        {
            "timestamp": "2024-09-14T10:42:04.055204+00:00",
            "processor": "MongoliaCatalogProcessor",
            "action": "created"
        }
    ]
}