{
    "nlm_catalog": "M0066171-025",
    "input_file_number": "W1NLM8253-I1NLM8253",
    "language(s)_of_the_main_text_(үндсэн_хэл)": "TIBETAN",
    "other_language(s)_in_the_main_text_(бусад_оролцсон_хэл)": "N",
    "full_title_(бүтэн_гарчиг)": "#, ,BCOM LDAN 'DAS MA SENG LDENG NAGS KYI SGROL MA'I BSTOD PA BZHUGS SO, ,",
    "colophon_(төгсгөлийн_үг)": "@007A *, ,(ZHES PA 'DI YANG SH'AKYA'I BTZUN PA BLO BZANG CHOS KYI RGYAL MTSAN DPAL BZANG POS CHOS GRVA CHEN PO DPAL LDAN 'BRAS SPUNGS SU SBYAR BA'O, ,'DI KYANG RGYAL BA GNYIS PA'I BSTAN PA RIN PO CHE DAR ZHING RGYAS LA YUN RING DU GNAS PAR GYUR CIG ,DGE'O, ,0",
    "author_simple": "BLO BZANG CHOS KYI RGYAL MTSAN,",
    "cover_type_(хавтасны_төрөл)": "N/A",
    "condition_of_book_(номын_төлөв_байдал)": "GOOD",
    "readability_of_book_(уншигдах_гаргацны_тухай)": "GOOD",
    "volume_(боть)": "N",
    "page_numbers_(хуудасны_дугаар)": "1A-7A",
    "size_of_printed_area_(дотоод_бичвэрийн_хэмжээ)": "16x6.5",
    "size_of_pages_(хуудасны_хэмжээ)": "22x9",
    "text_format_(бичвэрийн_төлөв)": "MS",
    "source": "National Library of Mongolia",
    "processing_history": [
        {
            "timestamp": "2024-09-14T16:27:01.196106+00:00",
            "processor": "MongoliaCatalogProcessor",
            "action": "created"
        }
    ]
}