{
    "name": "S05435E_MNGON PA KUN LAS BTUS PA'I RNAM BSHAD LEGS PAR BSHAD PA'I CHOS MNGON RGYA MTSO'I SNYING PO_@_RGYAL TSAB DAR MA RIN CHEN (1364-1432).TXT",
    "path": "MNGON PA_HIGHER KNOWLEDGE (ABHIDHARMA) (VAIBHASHIKA SCHOOL)/RGYAL TSAB DAR MA RIN CHEN_GYALTSAB DARMA RINCHEN (1364-1432)",
    "download_path": "/sungbum updated 7 30 23 nl/mngon pa_higher knowledge (abhidharma) (vaibhashika school)/rgyal tsab dar ma rin chen_gyaltsab darma rinchen (1364-1432)/s05435e_mngon pa kun las btus pa'i rnam bshad legs par bshad pa'i chos mngon rgya mtso'i snying po_@_rgyal tsab dar ma rin chen (1364-1432).txt",
    "file_id": "id:Ct2f7NF5r8EAAAAAAABmFg",
    "revision_id": "625a4b07d1e018d294473",
    "content_hash": "7bb25faa578b49f8f92b13111f29ebd646f66550d98c06398b96a609fe46c500",
    "server_modified": "2024-10-29 21:58:46",
    "last_sync": "2024-11-26 15:45:24.751087",
    "size": 615962,
    "meta_text": null,
    "cat_ref": "S05435E",
    "work_ref": "W.S05435E",
    "title_tib": "MNGON PA KUN LAS BTUS PA'I RNAM BSHAD LEGS PAR BSHAD PA'I CHOS MNGON RGYA MTSO'I SNYING PO",
    "title_eng": "",
    "source": "Asian Classics Input Project",
    "collection": "Sungbum",
    "language": "bo",
    "author_simple": "RGYAL TSAB DAR MA RIN CHEN",
    "subject": [
        {
            "_id": "225671928674",
            "subject_path": "GSUNG 'BUM_Sungbum/MNGON PA_HIGHER KNOWLEDGE (ABHIDHARMA) (VAIBHASHIKA SCHOOL)/RGYAL TSAB DAR MA RIN CHEN_GYALTSAB DARMA RINCHEN (1364-1432)",
            "subject_path_tibetan": "GSUNG 'BUM/MNGON PA/RGYAL TSAB DAR MA RIN CHEN",
            "subject_path_english": "Sungbum/HIGHER KNOWLEDGE (ABHIDHARMA) (VAIBHASHIKA SCHOOL)/GYALTSAB DARMA RINCHEN (1364-1432)",
            "subject_tibetan": "RGYAL TSAB DAR MA RIN CHEN",
            "subject_english": "GYALTSAB DARMA RINCHEN (1364-1432)"
        }
    ],
    "items": [],
    "author": [
        {
            "author_name": "RGYAL TSAB DAR MA RIN CHEN",
            "author_birth": "1364",
            "author_death": "1432",
            "bdrc_id": "bdr:P65",
            "normalized_name": "RGYAL TSAB DAR MA RIN CHEN",
            "bdrc_url": "http://purl.bdrc.io/resource/P65"
        }
    ],
    "path_history": [
        {
            "path": "GSUNG 'BUM_Sungbum/MNGON PA_HIGHER KNOWLEDGE (ABHIDHARMA) (VAIBHASHIKA SCHOOL)/RGYAL TSAB DAR MA RIN CHEN_GYALTSAB DARMA RINCHEN (1364-1432)",
            "timestamp": "2024-11-26 23:45:24.764049+00:00"
        }
    ],
    "processing_history": [
        {
            "timestamp": "2024-11-26T23:45:24.764049+00:00",
            "run_id": 1061,
            "processor": "dropbox_sync",
            "action": "created"
        }
    ],
    "content_type": "text"
}