{
    "name": "TD01599A_PHYIR ZLOG 'KHOR LO (---.txt",
    "path": "02 RGYUD_Diamond Way (Vajrayāna)/01 RNAL 'BYOR BLA MED_Unsurpassed Practice (Anuttara Yoga)/03 BDE MCHOG_Highest Bliss (Saṃvara)/02 YUM BKA'_Mother Texts (Mātṛ)/VOL 23 ('A)",
    "download_path": "/tengyur updated 10 31 24 ws/02 rgyud_diamond way (vajrayāna)/01 rnal 'byor bla med_unsurpassed practice (anuttara yoga)/03 bde mchog_highest bliss (saṃvara)/02 yum bka'_mother texts (mātṛ)/vol 23 ('a)/td01599a_phyir zlog 'khor lo (---.txt",
    "file_id": "id:Ct2f7NF5r8EAAAAAAAB65g",
    "revision_id": "62633c63e82d68d294473",
    "content_hash": "df041465d3f76dbd72db0340538802285535f4655f7d4982982a1f749d534ac7",
    "server_modified": "2024-11-06 00:41:11",
    "last_sync": "2024-11-20 03:59:55.436435",
    "size": 2915,
    "meta_text": null,
    "cat_ref": "TD01599A",
    "work_ref": "W.TD01599A",
    "title_tib": "PHYIR ZLOG 'KHOR LO (---",
    "title_eng": "",
    "source": "Asian Classics Input Project",
    "collection": "Tengyur",
    "language": "bo",
    "author_simple": "",
    "subject": [
        {
            "_id": "288969002893",
            "subject_path": "BSTAN 'GYUR_Tengyur/02 RGYUD_Diamond Way (Vajrayāna)/01 RNAL 'BYOR BLA MED_Unsurpassed Practice (Anuttara Yoga)/03 BDE MCHOG_Highest Bliss (Saṃvara)/02 YUM BKA'_Mother Texts (Mātṛ)/VOL 23 ('A)",
            "subject_path_tibetan": "BSTAN 'GYUR/02 RGYUD/01 RNAL 'BYOR BLA MED/03 BDE MCHOG/02 YUM BKA'/VOL 23 ('A)",
            "subject_path_english": "Tengyur/Diamond Way (Vajrayāna)/Unsurpassed Practice (Anuttara Yoga)/Highest Bliss (Saṃvara)/Mother Texts (Mātṛ)",
            "subject_tibetan": "VOL 23 ('A)",
            "subject_english": "Mother Texts (Mātṛ)"
        }
    ],
    "items": [],
    "author": [
        {
            "author_name": "",
            "author_birth": null,
            "author_death": null
        }
    ],
    "path_history": [
        {
            "path": "BSTAN 'GYUR_Tengyur/02 RGYUD_Diamond Way (Vajrayāna)/01 RNAL 'BYOR BLA MED_Unsurpassed Practice (Anuttara Yoga)/03 BDE MCHOG_Highest Bliss (Saṃvara)/02 YUM BKA'_Mother Texts (Mātṛ)/VOL 23 ('A)",
            "timestamp": "2024-11-20 11:59:55.473605+00:00"
        }
    ],
    "processing_history": [
        {
            "timestamp": "2024-11-20T11:59:55.473605+00:00",
            "run_id": 1025,
            "processor": "dropbox_sync",
            "action": "created"
        }
    ],
    "content_type": "text"
}