{
    "name": "TD03753_DPAL LHA MO NOR RGYUN MA'I DKYIL 'KHOR GYI CHO GA (Śrī Vasudhārā Devī Maṇḍala Vidhi).txt",
    "path": "BSTAN 'GYUR_Tengyur/02 RGYUD_Diamond Way (Vajrayāna)/VOL 78 (TSU)",
    "download_path": "/tengyur updated 10 31 24 ws/02 rgyud_diamond way (vajrayāna)/vol 78 (tsu)/td03753_dpal lha mo nor rgyun ma'i dkyil 'khor gyi cho ga (śrī vasudhārā devī maṇḍala vidhi).txt",
    "file_id": "id:Ct2f7NF5r8EAAAAAAAB4ww",
    "revision_id": "62633c0921df08d294473",
    "content_hash": "6faee3ea4eff1a41c3aca2769459a2edb642f7023d74ce78471f3cac547809ac",
    "server_modified": "2024-11-06 00:39:36",
    "last_sync": "2024-12-03 11:33:05.337736+00:00",
    "size": 11867,
    "cat_ref": "TD03753",
    "work_ref": "W.TD03753",
    "title_tib": "DPAL LHA MO NOR RGYUN MA'I DKYIL 'KHOR GYI CHO GA",
    "title_eng": "",
    "subject": [
        {
            "_id": "869790939477",
            "subject_path": "BSTAN 'GYUR_Tengyur/02 RGYUD_Diamond Way (Vajrayāna)/VOL 78 (TSU)",
            "subject_path_tibetan": "BSTAN 'GYUR/RGYUD/78 (TSU)",
            "subject_path_english": "Tengyur/Diamond Way (Vajrayāna)/VOL 78 (TSU)",
            "subject_tibetan": "78 (TSU)",
            "subject_english": "VOL 78 (TSU)"
        }
    ],
    "items": [],
    "source": "Asian Classics Input Project",
    "collection": "Tengyur",
    "title_skt": "Śrī Vasudhārā Devī Maṇḍala Vidhi",
    "processing_history": [
        {
            "timestamp": "2024-12-03T11:33:05.342104+00:00",
            "run_id": 1085,
            "processor": "dropbox_sync",
            "action": "created"
        }
    ],
    "updated": true,
    "update_reason": "new file",
    "path_history": [
        {
            "path": "BSTAN 'GYUR_Tengyur/BSTAN 'GYUR_Tengyur/02 RGYUD_Diamond Way (Vajrayāna)/VOL 78 (TSU)",
            "timestamp": "2024-12-03 11:33:05.342104+00:00"
        }
    ],
    "author": [],
    "content_type": "text"
}