{
    "name": "TD03143_'PHAGS PA SANGS RGYAS RJES SU DRAN PA (Ārya Buddhānusmṛti).txt",
    "path": "TENGYUR_TENGYUR/02 RGYUD_Diamond Way (Vajrayāna)/VOL 74 (PHU)",
    "download_path": "/tengyur updated 10 31 24 ws/02 rgyud_diamond way (vajrayāna)/vol 74 (phu)/td03143_'phags pa sangs rgyas rjes su dran pa (ārya buddhānusmṛti).txt",
    "file_id": "id:Ct2f7NF5r8EAAAAAAACDPw",
    "revision_id": "62633dd2e6ea28d294473",
    "content_hash": "b6142f91dd0b16ce271f4bc17b915ef6985a3bf08ae86ab6ae5579360ae22b8a",
    "server_modified": "2024-11-06 00:47:36",
    "last_sync": "2024-11-13 02:00:00.312679+00:00",
    "size": 1862,
    "cat_ref": "TD03143",
    "work_ref": "W.TD03143",
    "title_tib": "'PHAGS PA SANGS RGYAS RJES SU DRAN PA",
    "title_eng": "",
    "subject": [
        {
            "_id": "949406200925",
            "subject_path": "TENGYUR_TENGYUR/02 RGYUD_Diamond Way (Vajrayāna)/VOL 74 (PHU)",
            "subject_path_tibetan": "TENGYUR/RGYUD/74 (PHU)",
            "subject_path_english": "TENGYUR/Diamond Way (Vajrayāna)/VOL 74 (PHU)",
            "subject_tibetan": "74 (PHU)",
            "subject_english": "VOL 74 (PHU)"
        }
    ],
    "items": [],
    "source": "Asian Classics Input Project",
    "collection": "Tengyur",
    "title_skt": "Ārya Buddhānusmṛti",
    "processing_history": [
        {
            "timestamp": "2024-11-13T02:00:00.322565+00:00",
            "run_id": 926,
            "processor": "dropbox_sync",
            "action": "created"
        }
    ],
    "updated": true,
    "path_history": [
        {
            "path": "TENGYUR_TENGYUR/TENGYUR_TENGYUR/02 RGYUD_Diamond Way (Vajrayāna)/VOL 74 (PHU)",
            "timestamp": "2024-11-13 02:00:00.322565+00:00"
        }
    ],
    "author": []
}